pyknock/__init__.py
pyknock-0.4.3.data/scripts/pyknock-client
pyknock-0.4.3.data/scripts/pyknock-server
pyknock-0.4.3.dist-info/LICENSE
pyknock-0.4.3.dist-info/METADATA
pyknock-0.4.3.dist-info/WHEEL
pyknock-0.4.3.dist-info/top_level.txt
pyknock-0.4.3.dist-info/zip-safe
pyknock-0.4.3.dist-info/RECORD
