Metadata-Version: 2.1
Name: pyknock
Version: 0.4.3
Summary: UDP port knocking suite with HMAC-PSK authentication
Home-page: https://github.com/Snawoot/pyknock
Author: Vladislav Yarmak
Author-email: vladislav@vm-0.com
License: MIT
Platform: UNKNOWN
Classifier: Programming Language :: Python
Classifier: License :: OSI Approved :: MIT License
Classifier: Operating System :: OS Independent
Classifier: Development Status :: 5 - Production/Stable
Classifier: Environment :: No Input/Output (Daemon)
Classifier: Intended Audience :: System Administrators
Classifier: Natural Language :: English
Classifier: Topic :: Internet
Classifier: Topic :: System :: Networking :: Firewalls
Classifier: Topic :: Security
Classifier: Topic :: Utilities
Requires-Python: >=2.6
